s1081735/Q3/Q3.v
module Q3 (
           input clk,
           input num,
           output d5_s
       );


parameter IDLE = 3'b000;
parameter s_1   = 3'b001;
parameter s_2   = 3'b010;
parameter s_3   = 3'b011;
parameter s_4   = 3'b100;

reg [2:0] curr_state;
reg [2:0] next_state;
reg d5_s;

initial
begin
    curr_state = 0;
    d5_s = 0;
end

// output logic
always@(posedge clk)
begin
    case (curr_state)
        IDLE:
            d5_s = 1'b1;
        default:
            d5_s = 1'b0;
    endcase
end

// next state logic
always@(posedge clk)
begin
    case (curr_state)
        IDLE:
            if(num)
                next_state = s_1;
            else
                next_state = IDLE;
        s_1:
            if(num)
                next_state = s_3;
            else
                next_state = s_4;
        s_2:
            if(num)
                next_state = s_2;
            else
                next_state = s_1;
        s_3:
            if(num)
                next_state = s_4;
            else
                next_state = s_2;
        s_4:
            if(num)
                next_state = IDLE;
            else
                next_state = s_3;
        default :
            next_state = IDLE;

    endcase
    curr_state = next_state;
end
endmodule

s1081735/Q3/Q3_tb.v
module Q3_tb();

reg clk;
reg num;
wire d5_s;

// clk
always #5 clk = ~clk;

Q3 q3 (
       .clk (clk),
       .num (num),
       .d5_s (d5_s)
   );


initial
begin
    $dumpfile("Q3.vcd");
    $dumpvars;

    num=1'b0;
    clk = 1'b0;

    #4
     num=1'b1;

    #10
     $display("Input : %b , Output : %b",num,d5_s);
    num <= 1'b0;

    #10
     $display("Input : %b , Output : %b",num,d5_s);
    num <= 1'b1;

    #10
     $display("Input : %b , Output : %b",num,d5_s);
    num <= 1'b0;

    #10
     $display("Input : %b , Output : %b",num,d5_s);
    num <= 1'b0;

    #10
     $display("Input : %b , Output : %b",num,d5_s);

    $finish;

end

endmodule

s1081735/Q3/Q3.vcd
$date
	Wed Oct 12 16:35:46 2022
$end
$version
	Icarus Verilog
$end
$timescale
	1s
$end
$scope module Q3_tb $end
$var wire 1 ! d5_s $end
$var reg 1 " clk $end
$var reg 1 # num $end
$scope module q3 $end
$var wire 1 " clk $end
$var wire 1 # num $end
$var parameter 3 $ IDLE $end
$var parameter 3 % s_1 $end
$var parameter 3 & s_2 $end
$var parameter 3 ' s_3 $end
$var parameter 3 ( s_4 $end
$var reg 3 ) curr_state [2:0] $end
$var reg 1 ! d5_s $end
$var reg 3 * next_state [2:0] $end
$upscope $end
$upscope $end
$enddefinitions $end
$comment Show the parameter values. $end
$dumpall
b100 (
b11 '
b10 &
b1 %
b0 $
$end
#0
$dumpvars
bx *
b0 )
0#
0"
0!
$end
#4
1#
#5
b1 )
b1 *
1"
#10
0"
#14
0#
#15
b100 )
b100 *
1"
#20
0"
#24
1#
#25
1!
b0 )
b0 *
1"
#30
0"
#34
0#
